{
    "homepage": "http://boost.org/libs/units",
    "maintainers": [
        {
            "email": "daisuke.nishimatsu1021@gmail.com",
            "github": "wep21",
            "name": "Daisuke Nishimatsu"
        },
        {
            "email": "julian.amann@tum.de",
            "github": "Vertexwahn",
            "name": "Julian Amann"
        },
        {
            "email": "kgreenek@gmail.com",
            "github": "kgreenek",
            "name": "Kevin Greene"
        }
    ],
    "repository": [
        "github:boostorg/units"
    ],
    "versions": [
        "1.83.0"
    ],
    "yanked_versions": {}
}
