{
    "homepage": "https://github.com/bazel-contrib/rules_python",
    "maintainers": [
        {
            "name": "Richard Levasseur",
            "email": "richardlev@gmail.com",
            "github": "rickeylev",
            "github_user_id": 34175098
        },
        {
            "name": "Ignas Anikevicius",
            "email": "bcr-ignas@use.startmail.com",
            "github": "aignas",
            "github_user_id": 240938
        }
    ],
    "repository": [
        "github:bazelbuild/rules_python",
        "github:bazel-contrib/rules_python"
    ],
    "versions": [
        "2.0.0-rc2",
        "2.0.0-rc3",
        "2.0.0-rc4"
    ],
    "yanked_versions": {}
}
