{
    "homepage": "https://github.com/ClickHouse/clickhouse-cpp",
    "maintainers": [
        {
            "email": "andrew.slabko@clickhouse.com",
            "github": "slabko",
            "github_user_id": 5012202,
            "name": "Andrew Slabko"
        },
        {
            "email": "mikhail.shustov@clickhouse.com",
            "github": "mshustov",
            "github_user_id": 3198181,
            "name": "Mikhail Shustov"
        },
        {
            "email": "austin.bonander@clickhouse.com",
            "github": "abonander",
            "github_user_id": 3198595,
            "name": "Austin Bonander"
        }
    ],
    "repository": [
        "github:ClickHouse/clickhouse-cpp"
    ],
    "versions": [
        "2.6.1",
        "2.6.2"
    ],
    "yanked_versions": {}
}
