{
    "mediaType": "application/vnd.build.bazel.registry.attestation+json;version=1.0.0",
    "attestations": {
        "source.json": {
            "url": "https://github.com/bazel-contrib/tar.bzl/releases/download/v0.10.4/source.json.intoto.jsonl",
            "integrity": "sha256-DI042xNAHuRJBZdUi4Bw06SJF8oTpQ3wX0oA/KbduAs="
        },
        "MODULE.bazel": {
            "url": "https://github.com/bazel-contrib/tar.bzl/releases/download/v0.10.4/MODULE.bazel.intoto.jsonl",
            "integrity": "sha256-tT6leddsiH6gE//28Lk4sGDvvH/AWkihB3YFE50zHLc="
        },
        "tar.bzl-v0.10.4.tar.gz": {
            "url": "https://github.com/bazel-contrib/tar.bzl/releases/download/v0.10.4/tar.bzl-v0.10.4.tar.gz.intoto.jsonl",
            "integrity": "sha256-yhQB4l7D57P8ChRHISJE7ASAc7o9q2TFXmb8xvKmQsQ="
        }
    }
}
